webtoolkit/__init__.py
webtoolkit/baseurl.py
webtoolkit/contentinterface.py
webtoolkit/contentlinkparser.py
webtoolkit/contentmoderation.py
webtoolkit/contenttext.py
webtoolkit/crawlers/__init__.py
webtoolkit/crawlers/crawlerinterface.py
webtoolkit/crawlers/requestscrawler.py
webtoolkit/domaincache.py
webtoolkit/handlers/__init__.py
webtoolkit/handlers/defaulturlhandler.py
webtoolkit/handlers/handlerchannelodysee.py
webtoolkit/handlers/handlerchannelyoutube.py
webtoolkit/handlers/handlerhttppage.py
webtoolkit/handlers/handlerinterface.py
webtoolkit/handlers/handlers.py
webtoolkit/handlers/handlervideoodysee.py
webtoolkit/handlers/handlervideoyoutube.py
webtoolkit/pages.py
webtoolkit/remoteserver.py
webtoolkit/remoteurl.py
webtoolkit/request.py
webtoolkit/response.py
webtoolkit/statuses.py
webtoolkit/tests/__init__.py
webtoolkit/tests/fake/__init__.py
webtoolkit/tests/fake/codeproject.py
webtoolkit/tests/fake/firebog.py
webtoolkit/tests/fake/geekwirecom.py
webtoolkit/tests/fake/githubcom.py
webtoolkit/tests/fake/hackernews.py
webtoolkit/tests/fake/instance.py
webtoolkit/tests/fake/opmlfile.py
webtoolkit/tests/fake/reddit.py
webtoolkit/tests/fake/returndislike.py
webtoolkit/tests/fake/robotstxtcom.py
webtoolkit/tests/fake/thehill.py
webtoolkit/tests/fake/warhammercommunity.py
webtoolkit/tests/fake/youtube.py
webtoolkit/tests/fakeinternet.py
webtoolkit/tests/fakeinternetcontents.py
webtoolkit/tests/fakeresponse.py
webtoolkit/tests/mocks.py
webtoolkit/urllocation.py
webtoolkit/utils/dateutils.py
webtoolkit/utils/logger.py
webtoolkit/webconfig.py
webtoolkit/webtools.py
webtoolkit-0.0.191.dist-info/LICENSE
webtoolkit-0.0.191.dist-info/METADATA
webtoolkit-0.0.191.dist-info/WHEEL
webtoolkit-0.0.191.dist-info/RECORD
