Metadata-Version: 2.3
Name: webtoolkit
Version: 0.0.191
Summary: Web tools and interfaces for Internet data processing.
License: GPL3
Author: Iwan Grozny
Author-email: renegat@renegat0x0.ddns.net
Requires-Python: >=3.9,<4.0
Classifier: License :: Other/Proprietary License
Classifier: Programming Language :: Python :: 3
Classifier: Programming Language :: Python :: 3.9
Classifier: Programming Language :: Python :: 3.10
Classifier: Programming Language :: Python :: 3.11
Classifier: Programming Language :: Python :: 3.12
Classifier: Programming Language :: Python :: 3.13
Requires-Dist: beautifulsoup4 (>=4.13.5,<5.0.0)
Requires-Dist: brutefeedparser (>=0.10.5,<0.11.0)
Requires-Dist: lxml (>=5.4.0,<6.0.0)
Requires-Dist: psutil
Requires-Dist: python-dateutil (>=2.8.2,<3.0.0)
Requires-Dist: pytz (>=2024.2,<2025.0)
Requires-Dist: requests (>=2.32.3,<3.0.0)
Requires-Dist: tldextract (>=5.1.2,<6.0.0)
Requires-Dist: ua-generator (>=2.0.17,<3.0.0)
Requires-Dist: url-cleaner
